{
  "info": {
    "_postman_id": "5b3f42a9-9806-4501-9acf-35f9e9870659",
    "name": "WebServiceAPI",
    "schema": "https://schema.getpostman.com/json/collection/v2.1.0/collection.json",
    "_exporter_id": "47273611",
    "_collection_link": "https://go.postman.co/collection/47273611-5b3f42a9-9806-4501-9acf-35f9e9870659?source=collection_link"
  },
  "item": [
    {
      "name": "Get All Coffees",
      "event": [
        {
          "listen": "test",
          "script": {
            "exec": [
              "pm.test(\"Status code is 200\", function () {\r",
              "    pm.response.to.have.status(200);\r",
              "});"
            ],
            "type": "text/javascript",
            "packages": {},
            "requests": {}
          }
        }
      ],
      "request": {
        "method": "GET",
        "header": [
          {
            "key": "accept",
            "value": "text/plain"
          }
        ],
        "url": {
          "raw": "https://webservice.toscacloud.com/api/v1/Coffees",
          "protocol": "https",
          "host": [
            "webservice",
            "toscacloud",
            "com"
          ],
          "path": [
            "api",
            "v1",
            "Coffees"
          ]
        },
        "description": "Generated from cURL: curl -X 'GET'  \n'[https://webservice.toscacloud.com/api/v1/Coffees'](https://webservice.toscacloud.com/api/v1/Coffees')  \n\\-H 'accept: text/plain'"
      },
      "response": []
    }
  ]
}